pki/__init__.py
pki/__main__.py
pki/cli.py
pypki-0.0.1.dist-info/AUTHORS.rst
pypki-0.0.1.dist-info/LICENSE
pypki-0.0.1.dist-info/METADATA
pypki-0.0.1.dist-info/WHEEL
pypki-0.0.1.dist-info/entry_points.txt
pypki-0.0.1.dist-info/top_level.txt
pypki-0.0.1.dist-info/RECORD
