Metadata-Version: 2.1
Name: pypki
Version: 0.0.1
Summary: Managing PKI systems
Home-page: https://github.com/hlevering/pypki
Author: Hendrik Levering
Author-email: h.levering.git@gmail.com
License: BSD-2-Clause
Project-URL: Documentation, https://pypki.readthedocs.io/
Project-URL: Changelog, https://pypki.readthedocs.io/en/latest/changelog.html
Project-URL: Issue Tracker, https://github.com/hlevering/pypki/issues
Platform: UNKNOWN
Classifier: Development Status :: 5 - Production/Stable
Classifier: Intended Audience :: Developers
Classifier: License :: OSI Approved :: BSD License
Classifier: Operating System :: Unix
Classifier: Operating System :: POSIX
Classifier: Operating System :: Microsoft :: Windows
Classifier: Programming Language :: Python
Classifier: Programming Language :: Python :: 3
Classifier: Programming Language :: Python :: 3.6
Classifier: Programming Language :: Python :: 3.7
Classifier: Programming Language :: Python :: 3.8
Classifier: Programming Language :: Python :: Implementation :: CPython
Classifier: Topic :: Utilities
Requires-Python: >=3.6l
